uds/__init__.py
uds/config.py
uds/factories.py
uds/interfaces.py
uds/uds_communications/__init__.py
uds/uds_communications/TransportProtocols/__init__.py
uds/uds_communications/TransportProtocols/Can/CanTp.py
uds/uds_communications/TransportProtocols/Can/CanTpTypes.py
uds/uds_communications/TransportProtocols/Can/__init__.py
uds/uds_communications/Uds/Uds.py
uds/uds_communications/Uds/__init__.py
uds/uds_communications/Utilities/ResettableTimer.py
uds/uds_communications/Utilities/UtilityFunctions.py
uds/uds_communications/Utilities/__init__.py
uds/uds_communications/Utilities/iResettableTimer.py
uds/uds_config_tool/DecodeFunctions.py
uds/uds_config_tool/IHexFunctions.py
uds/uds_config_tool/UdsConfigTool.py
uds/uds_config_tool/UtilityFunctions.py
uds/uds_config_tool/__init__.py
uds/uds_config_tool/FunctionCreation/ClearDTCMethodFactory.py
uds/uds_config_tool/FunctionCreation/DiagnosticSessionControlMethodFactory.py
uds/uds_config_tool/FunctionCreation/ECUResetMethodFactory.py
uds/uds_config_tool/FunctionCreation/InputOutputControlMethodFactory.py
uds/uds_config_tool/FunctionCreation/ReadDTCMethodFactory.py
uds/uds_config_tool/FunctionCreation/ReadDataByIdentifierMethodFactory.py
uds/uds_config_tool/FunctionCreation/RequestDownloadMethodFactory.py
uds/uds_config_tool/FunctionCreation/RequestUploadMethodFactory.py
uds/uds_config_tool/FunctionCreation/RoutineControlMethodFactory.py
uds/uds_config_tool/FunctionCreation/SecurityAccessMethodFactory.py
uds/uds_config_tool/FunctionCreation/TesterPresentMethodFactory.py
uds/uds_config_tool/FunctionCreation/TransferDataMethodFactory.py
uds/uds_config_tool/FunctionCreation/TransferExitMethodFactory.py
uds/uds_config_tool/FunctionCreation/WriteDataByIdentifierMethodFactory.py
uds/uds_config_tool/FunctionCreation/__init__.py
uds/uds_config_tool/FunctionCreation/iServiceMethodFactory.py
uds/uds_config_tool/ISOStandard/ISOStandard.py
uds/uds_config_tool/ISOStandard/__init__.py
pykiso_python_uds-3.2.1.dist-info/LICENSE.md
pykiso_python_uds-3.2.1.dist-info/METADATA
pykiso_python_uds-3.2.1.dist-info/WHEEL
pykiso_python_uds-3.2.1.dist-info/top_level.txt
pykiso_python_uds-3.2.1.dist-info/RECORD
